fastk/Histex.so
fastk/Profex.so
fastk/_Histex.py
fastk/_Profex.py
fastk/__init__.py
fastk/setup.py
fastk-1.1.dist-info/licenses/LICENSE
fastk-1.1.dist-info/licenses/LICENSE.FASTK
fastk-1.1.dist-info/METADATA
fastk-1.1.dist-info/WHEEL
fastk-1.1.dist-info/top_level.txt
fastk-1.1.dist-info/RECORD
