Metadata-Version: 2.4
Name: fastk
Version: 1.1
Summary: Python wrappers for FastK tools
Home-page: https://github.com/yoshihikosuzuki/FASTK_python
Author: Yoshihiko Suzuki
Author-email: yoshi.suzuki.1992@gmail.com
Requires-Python: >=3
License-File: LICENSE
License-File: LICENSE.FASTK
Requires-Dist: bits-yoshi>=0.1.1
Dynamic: license-file
